num2tex/__init__.py
num2tex-0.8.dist-info/LICENSE
num2tex-0.8.dist-info/METADATA
num2tex-0.8.dist-info/WHEEL
num2tex-0.8.dist-info/top_level.txt
num2tex-0.8.dist-info/RECORD
