Metadata-Version: 2.1
Name: num2tex
Version: 0.8
Summary: Convert float or int to a TeX-formatted string
Home-page: http://github.com/AndrewChap/num2tex
Author: Andrew Chap
Author-email: andrew@andrewchap.com
License: MIT
Platform: UNKNOWN
